statmach.py
statmach-1.0.10.dist-info/LICENSE
statmach-1.0.10.dist-info/METADATA
statmach-1.0.10.dist-info/WHEEL
statmach-1.0.10.dist-info/top_level.txt
statmach-1.0.10.dist-info/RECORD
