Metadata-Version: 2.1
Name: statmach
Version: 1.0.10
Summary: Pythonic Finite State Machine with both action outputs (Mearly) and state outputs (Moore).
Home-page: https://github.com/hlovatt/statmach
Author: Howard C Lovatt.
Author-email: howard.lovatt@gmail.com
License: LIT License
Platform: any
Classifier: Intended Audience :: Developers
Classifier: Programming Language :: Python :: 3
Classifier: License :: OSI Approved :: MIT License
Classifier: Operating System :: OS Independent
Requires-Python: >=3.5
